tkseem/__init__.py
tkseem/_base.py
tkseem/character_tokenizer.py
tkseem/disjoint_letters_tokenizer.py
tkseem/morphological_tokenizer.py
tkseem/random_tokenizder.py
tkseem/sentencepiece_tokenizer.py
tkseem/tokenizers.py
tkseem/util.py
tkseem/word_tokenizer.py
tkseem/dictionaries/cached.pl
tkseem/dictionaries/vocab.pl
tkseem-0.0.3.dist-info/LICENSE
tkseem-0.0.3.dist-info/METADATA
tkseem-0.0.3.dist-info/WHEEL
tkseem-0.0.3.dist-info/top_level.txt
tkseem-0.0.3.dist-info/RECORD
