Metadata-Version: 2.1
Name: tkseem
Version: 0.0.3
Summary: UNKNOWN
Home-page: https://github.com/MagedSaeed/tkseem
Author: Zaid Alyafeai, Maged Saeed
Author-email: arabicmachinelearning@gmail.com
License: MIT
Platform: UNKNOWN
Requires-Python: >=3.6
Requires-Dist: sentencepiece
Requires-Dist: farasapy
Requires-Dist: tqdm
Requires-Dist: numpy
Requires-Dist: black
